maharashtra_forts/__init__.py
maharashtra_forts/get_forts.py
maharashtra_forts/maharashtra_forts.py
maharashtra_forts/forts/__init__.py
maharashtra_forts/forts/harishchandragad_fort.py
maharashtra_forts/forts/lohagad_fort.py
maharashtra_forts/forts/pratapgad_fort.py
maharashtra_forts/forts/purandar_fort.py
maharashtra_forts/forts/raigad_fort.py
maharashtra_forts/forts/rajgad_fort.py
maharashtra_forts/forts/shivneri_fort.py
maharashtra_forts/forts/sinhagad_fort.py
maharashtra_forts/forts/tikona_fort.py
maharashtra_forts/forts/torna_fort.py
maharashtra_forts-0.8.dist-info/METADATA
maharashtra_forts-0.8.dist-info/WHEEL
maharashtra_forts-0.8.dist-info/top_level.txt
maharashtra_forts-0.8.dist-info/RECORD
