Metadata-Version: 2.1
Name: maharashtra-forts
Version: 0.8
Summary: A Python library for exploring forts in Maharashtra
Home-page: https://github.com/your-username/maharashtra-forts
Author: Rahul Bhoyar
Author-email: rahulbhoyaroffice@gmail.com
License: UNKNOWN
Platform: UNKNOWN
Classifier: Programming Language :: Python :: 3
Classifier: License :: OSI Approved :: MIT License
Classifier: Operating System :: OS Independent
Requires-Python: >=3.6
